ipc_enums/__init__.py
ipc_enums/share.py
ipc_enums-0.0.6.dist-info/METADATA
ipc_enums-0.0.6.dist-info/RECORD
ipc_enums-0.0.6.dist-info/WHEEL
ipc_enums-0.0.6.dist-info/top_level.txt
