Metadata-Version: 2.1
Name: ipc-enums
Version: 0.0.6
Summary: shared enum types
Home-page: https://blog.huangyu.me
Author: Yu Huang
Author-email: diwang90@qq.com
License: UNKNOWN
Platform: UNKNOWN
Classifier: Programming Language :: Python :: 3
Classifier: License :: OSI Approved :: MIT License
Classifier: Operating System :: OS Independent
